LICENSE
MANIFEST.in
README.rst
setup.cfg
setup.py
dukpy/__init__.py
dukpy/babel.py
dukpy/coffee.py
dukpy/evaljs.py
dukpy/install.py
dukpy/lessc.py
dukpy/module_loader.py
dukpy/nodelike.py
dukpy/run.py
dukpy/tsc.py
dukpy/jscore/fs.js
dukpy/jscore/path.js
dukpy/jscore/punycode.js
dukpy/jscore/querystring.js
dukpy/jscore/url.js
dukpy/jsmodules/babel-6.26.0.min.js
dukpy/jsmodules/coffeescript.js
dukpy/jsmodules/semver.js
dukpy/jsmodules/typescriptServices.js
dukpy/jsmodules/less/less/contexts.js
dukpy/jsmodules/less/less/import-manager.js
dukpy/jsmodules/less/less/index.js
dukpy/jsmodules/less/less/less-error.js
dukpy/jsmodules/less/less/logger.js
dukpy/jsmodules/less/less/parse-tree.js
dukpy/jsmodules/less/less/parse.js
dukpy/jsmodules/less/less/plugin-manager.js
dukpy/jsmodules/less/less/render.js
dukpy/jsmodules/less/less/source-map-builder.js
dukpy/jsmodules/less/less/source-map-output.js
dukpy/jsmodules/less/less/transform-tree.js
dukpy/jsmodules/less/less/utils.js
dukpy/jsmodules/less/less-node/environment.js
dukpy/jsmodules/less/less-node/file-manager.js
dukpy/jsmodules/less/less-node/fs.js
dukpy/jsmodules/less/less-node/image-size.js
dukpy/jsmodules/less/less-node/index.js
dukpy/jsmodules/less/less-node/lessc-helper.js
dukpy/jsmodules/less/less-node/plugin-loader.js
dukpy/jsmodules/less/less-node/url-file-manager.js
dukpy/jsmodules/less/less/data/colors.js
dukpy/jsmodules/less/less/data/index.js
dukpy/jsmodules/less/less/data/unit-conversions.js
dukpy/jsmodules/less/less/environment/abstract-file-manager.js
dukpy/jsmodules/less/less/environment/environment-api.js
dukpy/jsmodules/less/less/environment/environment.js
dukpy/jsmodules/less/less/environment/file-manager-api.js
dukpy/jsmodules/less/less/functions/color-blending.js
dukpy/jsmodules/less/less/functions/color.js
dukpy/jsmodules/less/less/functions/data-uri.js
dukpy/jsmodules/less/less/functions/default.js
dukpy/jsmodules/less/less/functions/function-caller.js
dukpy_timeout.egg-info/PKG-INFO
dukpy_timeout.egg-info/SOURCES.txt
dukpy_timeout.egg-info/dependency_links.txt
dukpy_timeout.egg-info/entry_points.txt
dukpy_timeout.egg-info/requires.txt
dukpy_timeout.egg-info/top_level.txt
