Metadata-Version: 2.1
Name: dukpy-timeout
Version: 0.0.1
Summary: Fork of dukpy, patched with timeout support
Home-page: https://github.com/rmb122/dukpy_timeout
Author: rmb122
Author-email: pypi@rmb122.com
License: MIT
Project-URL: CI: AppVeyor, https://ci.appveyor.com/project/rmb122/dukpy_timeout
Project-URL: CI: Travis, https://travis-ci.org/rmb122/dukpy_timeout
Project-URL: GitHub: issues, https://github.com/rmb122/dukpy_timeout/issues
Project-URL: GitHub: repo, https://github.com/rmb122/dukpy_timeout
Keywords: javascript compiler babeljs jsx coffeescript typescript timeout
Classifier: Development Status :: 3 - Alpha
Classifier: License :: OSI Approved :: MIT License
Classifier: Programming Language :: Python :: 3.8
Classifier: Programming Language :: Python :: 3.7
Classifier: Programming Language :: Python :: 3.6
Classifier: Programming Language :: Python :: 3.5
Classifier: Programming Language :: Python :: 2.7
Classifier: Programming Language :: JavaScript
Provides-Extra: testing
Provides-Extra: webassets
License-File: LICENSE
